PoorWSGI-2.7.0.data/data/share/doc/poorwsgi/CONTRIBUTION.rst
PoorWSGI-2.7.0.data/data/share/doc/poorwsgi/ChangeLog
PoorWSGI-2.7.0.data/data/share/doc/poorwsgi/README.rst
PoorWSGI-2.7.0.data/data/share/doc/poorwsgi/licence.txt
PoorWSGI-2.7.0.data/data/share/poorwsgi/examples/http_digest.py
PoorWSGI-2.7.0.data/data/share/poorwsgi/examples/large_file.py
PoorWSGI-2.7.0.data/data/share/poorwsgi/examples/metrics.py
PoorWSGI-2.7.0.data/data/share/poorwsgi/examples/openapi.json
PoorWSGI-2.7.0.data/data/share/poorwsgi/examples/openapi3.py
PoorWSGI-2.7.0.data/data/share/poorwsgi/examples/put_file.py
PoorWSGI-2.7.0.data/data/share/poorwsgi/examples/simple.py
PoorWSGI-2.7.0.data/data/share/poorwsgi/examples/simple_json.py
PoorWSGI-2.7.0.data/data/share/poorwsgi/examples/test.digest
PoorWSGI-2.7.0.data/data/share/poorwsgi/examples/websocket.py
poorwsgi/__init__.py
poorwsgi/digest.py
poorwsgi/fieldstorage.py
poorwsgi/headers.py
poorwsgi/openapi_wrapper.py
poorwsgi/py.typed
poorwsgi/request.py
poorwsgi/response.py
poorwsgi/results.py
poorwsgi/session.py
poorwsgi/state.py
poorwsgi/wsgi.py
PoorWSGI-2.7.0.dist-info/METADATA
PoorWSGI-2.7.0.dist-info/WHEEL
PoorWSGI-2.7.0.dist-info/top_level.txt
PoorWSGI-2.7.0.dist-info/RECORD
