Metadata-Version: 2.1
Name: PoorWSGI
Version: 2.7.0
Summary: Poor WSGI connector for Python
Home-page: http://poorhttp.zeropage.cz/poorwsgi
Author: Ondřej Tůma
Author-email: mcbig@zeropage.cz
Maintainer: Ondrej Tuma
Maintainer-email: mcbig@zeropage.cz
License: BSD
Project-URL: Documentation, http://poorhttp.zeropage.cz/poorwsgi
Project-URL: Funding, https://github.com/sponsors/ondratu
Project-URL: Source, https://github.com/poorHttp/PoorWSGI
Project-URL: Tracker, https://github.com/PoorHttp/PoorWSGI/issues
Keywords: web wsgi development
Classifier: Development Status :: 5 - Production/Stable
Classifier: Environment :: Web Environment
Classifier: Intended Audience :: Developers
Classifier: License :: OSI Approved :: BSD License
Classifier: Natural Language :: English
Classifier: Natural Language :: Czech
Classifier: Operating System :: MacOS :: MacOS X
Classifier: Operating System :: POSIX
Classifier: Operating System :: POSIX :: BSD
Classifier: Operating System :: POSIX :: Linux
Classifier: Programming Language :: Python :: 3 :: Only
Classifier: Topic :: Internet :: WWW/HTTP :: Dynamic Content
Classifier: Topic :: Internet :: WWW/HTTP :: WSGI :: Middleware
Classifier: Topic :: Software Development :: Libraries :: Python Modules
Requires-Python: >=3.8
Provides-Extra: jsongeneratorresponse
Requires-Dist: simplejson ; extra == 'jsongeneratorresponse'
